userverse_python_client/__init__.py
userverse_python_client/error_model.py
userverse_python_client/http_client_base.py
userverse_python_client/response_messages.py
userverse_python_client/clients/__init__.py
userverse_python_client/clients/company.py
userverse_python_client/clients/company_user_management.py
userverse_python_client/clients/company_user_roles_management.py
userverse_python_client/clients/user.py
userverse_python_client-0.1.12.dist-info/METADATA
userverse_python_client-0.1.12.dist-info/WHEEL
userverse_python_client-0.1.12.dist-info/licenses/LICENSE
userverse_python_client-0.1.12.dist-info/RECORD
