Metadata-Version: 2.4
Name: userverse-python-client
Version: 0.1.12
Summary: Add your description here
Author-email: skhendle@gmail.com
License-File: LICENSE
Requires-Python: >=3.12
Requires-Dist: black>=25.9.0
Requires-Dist: fastapi>=0.119.0
Requires-Dist: requests>=2.32.5
Requires-Dist: shared-models>=0.1.10
